dmpy/__init__.py
dmpy/distributedmake.py
dmpy/objects/__init__.py
dmpy/objects/dm_rule.py
dmpy/testing/__init__.py
dmpy/testing/makefile_parser.py
dmpy-0.21.0.dist-info/DESCRIPTION.rst
dmpy-0.21.0.dist-info/METADATA
dmpy-0.21.0.dist-info/RECORD
dmpy-0.21.0.dist-info/WHEEL
dmpy-0.21.0.dist-info/metadata.json
dmpy-0.21.0.dist-info/top_level.txt
