Metadata-Version: 2.0
Name: dmpy
Version: 0.21.0
Summary: Distributed Make for Python
Home-page: https://github.com/kvg/dmpy
Author: Kiran Garimella, Warren Kretzschmar
Author-email: kiran.garimella@gmail.com, winni@warrenwk.com
License: UNKNOWN
Platform: UNKNOWN
Requires-Dist: attrs
